{
  "id": "pptx-ladder-04-kerning-accent-highlight",
  "kind": "pptx",
  "input": "../../../tests/Lokad.OoxPdf.Tests/Cases/pptx-ladder-04-kerning-accent-highlight.pptx",
  "dpi": 144,
  "tags": ["pptx", "ladder", "styled-text", "kerning", "accent", "highlight"],
  "expected": {
    "minAgentRating": 3,
    "pageCountMustMatch": true,
    "dimensionsMustMatch": true,
    "diagnosticsMustBeEmpty": true,
    "maxMeanAbsoluteError": 0.315,
    "maxChangedPixelRatioAtThreshold16": 0.0063
  },
  "allowedUnsupportedFeatures": []
}
